helpvester/__init__.py
helpvester-0.1.0.dist-info/WHEEL
helpvester-0.1.0.dist-info/METADATA
helpvester-0.1.0.dist-info/RECORD
