Metadata-Version: 2.1
Name: helpvester
Version: 0.1.0
Summary: Utility for harvesting program parameter descriptions from executables
Author: Pawel Zukowski
Author-email: p.z.idlecode@gmail.com
Requires-Python: >=3.8,<4.0
Classifier: Programming Language :: Python :: 3
Classifier: Programming Language :: Python :: 3.8
